[
    {
        "id": 317,
        "title": "Friendship Relation",
        "problem_statement": "<div class=\\\"problem-container\\\">\n    <h2 class=\\\"problem-title\\\">Friendship Relation</h2>\n    \n    <div class=\\\"problem-description\\\">\n        <p>There are N students in the college. We have M friendship relations between pairs of students (i.e., for pair (u, v), u and v are said to be friends with each other).</p>\n        \n        <p>The friendship relation is transitive, meaning that if pairs (a, b) and (b, c) exist, then we can assume that (a, c) also exists.</p>\n        \n        <p>You need to find the minimum number of additional friendship relations that need to be added so that all N students will be friends with each other.</p>\n    </div>\n\n    <div class=\\\"function-description\\\">\n        <h3>Function Description</h3>\n        <p>Complete the <code>solve()</code> function. The function takes the following 2 parameters and returns an integer denoting the answer to the question:</p>\n        <ul>\n            <li><code>N</code>: Represents the number of elements in the array</li>\n            <li><code>Friends</code>: Represents a list of M pairs - denoting the friendship relations</li>\n        </ul>\n    </div>\n    \n    <div class=\\\"input-format\\\">\n        <h3>Input Format</h3>\n        <p>Note: Use this input format if you are testing against custom input or writing code in a language where we don\\'t provide boilerplate code.</p>\n        <ul>\n            <li>The first line contains a single integer N denoting the number of elements in the array.</li>\n            <li>The second line contains a single integer M denoting the number of friendship relations.</li>\n            <li>Each of the next M lines contains two space-separated integers, u and v, denoting the friendship relation between u and v.</li>\n        </ul>\n        <p>It is guaranteed that u ≠ v and a relation pair (u, v) occurs not more than once in the input.</p>\n    </div>\n    \n    <div class=\\\"output-format\\\">\n        <h3>Output Format</h3>\n        <p>Print an integer answer to the question.</p>\n    </div>\n    \n    <div class=\\\"constraints\\\">\n        <h3>Constraints</h3>\n        <ul>\n            <li>1 ≤ N ≤ 2 * 10<sup>5</sup></li>\n            <li>1 ≤ u, v ≤ N</li>\n            <li>0 ≤ M ≤ min(3 * 10<sup>6</sup>, N * (N - 1)/2)</li>\n        </ul>\n    </div>\n    \n    <div class=\\\"examples\\\">\n        <h3>Sample Test Case</h3>\n        <div class=\\\"example\\\">\n            <pre class=\\\"input\\\">4\n3\n1 2\n2 3\n1 3</pre>\n            <pre class=\\\"output\\\">1</pre>\n        </div>\n    </div>\n</div>\n\n<style>\n.problem-container {\n    max-width: 800px;\n    margin: 0 auto;\n    padding: 20px;\n}\n\n.problem-title {\n    color: #333;\n    border-bottom: 2px solid #eee;\n    padding-bottom: 10px;\n}\n\ncode {\n    background-color: #f5f5f5;\n    padding: 2px 4px;\n    border-radius: 4px;\n    font-family: monospace;\n}\n\npre {\n    background-color: #f5f5f5;\n    padding: 15px;\n    border-radius: 4px;\n    overflow-x: auto;\n}\n\n.example {\n    margin: 20px 0;\n    padding: 15px;\n    border: 1px solid #eee;\n    border-radius: 4px;\n}\n\n.constraints ul {\n    list-style-type: none;\n    padding-left: 0;\n}\n\n.constraints li {\n    margin: 5px 0;\n}\n</style>",
        "google_doc_link": "https://docs.google.com/document/d/1-m3VlWdQCfGJdwV3HcfxFaf5CDvqVq6Nnuf0wHKyw9c/edit?usp=sharing",
        "solution_code": "",
        "company_name": "Pocketpills",
        "company_id": 96
    }
]